yir/__init__.py
yir/version.py
yir/relay/__init__.py
yir/relay/ir_visualizer.py
yir-0.1.0rc1.dist-info/LICENSE
yir-0.1.0rc1.dist-info/METADATA
yir-0.1.0rc1.dist-info/WHEEL
yir-0.1.0rc1.dist-info/top_level.txt
yir-0.1.0rc1.dist-info/RECORD
