Metadata-Version: 2.1
Name: yir
Version: 0.1.0rc1
Summary: Yet another IR
Home-page: https://github.com/zhiqwang/yir
Author: Zhiqiang Wang
Author-email: me@zhiqwang.com
License: Apache License 2.0
Project-URL: Bug Reports, https://github.com/zhiqwang/yir/issues
Project-URL: Funding, https://zhiqwang.com
Project-URL: Source, https://github.com/zhiqwang/yir/
Keywords: machine-learning,deep-learning,ir
Platform: UNKNOWN
Classifier: Operating System :: OS Independent
Classifier: Development Status :: 4 - Beta
Classifier: Intended Audience :: Developers
Classifier: Topic :: Education
Classifier: Topic :: Scientific/Engineering
Classifier: Topic :: Scientific/Engineering :: Artificial Intelligence
Classifier: Topic :: Scientific/Engineering :: Image Recognition
Classifier: License :: OSI Approved :: Apache Software License
Classifier: Programming Language :: Python :: 3
Classifier: Programming Language :: Python :: 3.6
Classifier: Programming Language :: Python :: 3.7
Classifier: Programming Language :: Python :: 3.8
Classifier: Programming Language :: Python :: 3.9
Requires-Python: >=3.6, <4
License-File: LICENSE
Requires-Dist: graphviz
